setup.py
python_wink.egg-info/PKG-INFO
python_wink.egg-info/SOURCES.txt
python_wink.egg-info/dependency_links.txt
python_wink.egg-info/requires.txt
python_wink.egg-info/top_level.txt
python_wink.egg-info/zip-safe
pywink/__init__.py
pywink/api.py
pywink/devices/__init__.py
pywink/devices/air_conditioner.py
pywink/devices/base.py
pywink/devices/binary_switch.py
pywink/devices/binary_switch_group.py
pywink/devices/button.py
pywink/devices/camera.py
pywink/devices/cloud_clock.py
pywink/devices/eggtray.py
pywink/devices/factory.py
pywink/devices/fan.py
pywink/devices/gang.py
pywink/devices/garage_door.py
pywink/devices/hub.py
pywink/devices/key.py
pywink/devices/light_bulb.py
pywink/devices/light_group.py
pywink/devices/lock.py
pywink/devices/piggy_bank.py
pywink/devices/powerstrip.py
pywink/devices/propane_tank.py
pywink/devices/remote.py
pywink/devices/robot.py
pywink/devices/scene.py
pywink/devices/sensor.py
pywink/devices/shade.py
pywink/devices/shade_group.py
pywink/devices/siren.py
pywink/devices/smoke_detector.py
pywink/devices/sprinkler.py
pywink/devices/thermostat.py
pywink/devices/types.py
pywink/devices/water_heater.py