Metadata-Version: 1.0
Name: python-wink
Version: 1.10.5
Summary: Access Wink devices via the Wink API
Home-page: http://github.com/python-wink/python-wink
Author: Brad Johnson, William Scanlon
Author-email: UNKNOWN
License: MIT
Platform: UNKNOWN
